{"$schema":"http://cyclonedx.org/schema/bom-1.6.schema.json","bomFormat":"CycloneDX","specVersion":"1.6","serialNumber":"urn:uuid:09ffb3f5-85fc-4091-ba87-aebefa2b83a5","version":1,"metadata":{"timestamp":"2025-01-14T19:36:54+01:00","tools":{"components":[{"type":"application","author":"anchore","name":"syft","version":"1.18.1"}]},"component":{"bom-ref":"751fdbc2377e110a","type":"file","name":"Repositories\\szenius-notion-burndown"}},"components":[{"bom-ref":"81f72c911a2909ae","type":"library","name":"./","version":"UNKNOWN","cpe":"cpe:2.3:a:.\\/:.\\/:*:*:*:*:*:*:*:*","properties":[{"name":"syft:package:foundBy","value":"github-actions-usage-cataloger"},{"name":"syft:package:type","value":"github-action"},{"name":"syft:location:0:path","value":"\\.github\\workflows\\sprint_daily.yml"}]},{"bom-ref":"81b013141ff5dff5","type":"library","name":"./","version":"UNKNOWN","cpe":"cpe:2.3:a:.\\/:.\\/:*:*:*:*:*:*:*:*","properties":[{"name":"syft:package:foundBy","value":"github-actions-usage-cataloger"},{"name":"syft:package:type","value":"github-action"},{"name":"syft:location:0:path","value":"\\.github\\workflows\\sprint_daily_manual.yml"}]},{"bom-ref":"87055fa98740fa27","type":"library","name":"./","version":"UNKNOWN","cpe":"cpe:2.3:a:.\\/:.\\/:*:*:*:*:*:*:*:*","properties":[{"name":"syft:package:foundBy","value":"github-actions-usage-cataloger"},{"name":"syft:package:type","value":"github-action"},{"name":"syft:location:0:path","value":"\\.github\\workflows\\sprint_start.yml"}]},{"bom-ref":"e32657faa6595567","type":"library","name":"./","version":"UNKNOWN","cpe":"cpe:2.3:a:.\\/:.\\/:*:*:*:*:*:*:*:*","properties":[{"name":"syft:package:foundBy","value":"github-actions-usage-cataloger"},{"name":"syft:package:type","value":"github-action"},{"name":"syft:location:0:path","value":"\\.github\\workflows\\sprint_start_manual.yml"}]},{"bom-ref":"pkg:npm/%40actions/core@1.6.0?package-id=57a8f74d0380c33c","type":"library","name":"@actions/core","version":"1.6.0","cpe":"cpe:2.3:a:toolkit_project:toolkit:1.6.0:*:*:*:*:node.js:*:*","purl":"pkg:npm/%40actions/core@1.6.0","properties":[{"name":"syft:package:foundBy","value":"javascript-lock-cataloger"},{"name":"syft:package:language","value":"javascript"},{"name":"syft:package:type","value":"npm"},{"name":"syft:package:metadataType","value":"javascript-npm-package-lock-entry"},{"name":"syft:cpe23","value":"cpe:2.3:a:github:toolkit:1.6.0:*:*:*:*:node.js:*:*"},{"name":"syft:location:0:path","value":"\\package-lock.json"}]},{"bom-ref":"pkg:npm/%40actions/github@5.0.1?package-id=3aa7b8165a2d1a7c","type":"library","name":"@actions/github","version":"5.0.1","cpe":"cpe:2.3:a:\\@actions\\/github:\\@actions\\/github:5.0.1:*:*:*:*:*:*:*","purl":"pkg:npm/%40actions/github@5.0.1","properties":[{"name":"syft:package:foundBy","value":"javascript-lock-cataloger"},{"name":"syft:package:language","value":"javascript"},{"name":"syft:package:type","value":"npm"},{"name":"syft:package:metadataType","value":"javascript-npm-package-lock-entry"},{"name":"syft:location:0:path","value":"\\package-lock.json"}]},{"bom-ref":"pkg:npm/%40actions/http-client@1.0.11?package-id=3e3fc1b3023c401b","type":"library","name":"@actions/http-client","version":"1.0.11","cpe":"cpe:2.3:a:\\@actions\\/http-client:\\@actions\\/http-client:1.0.11:*:*:*:*:*:*:*","purl":"pkg:npm/%40actions/http-client@1.0.11","properties":[{"name":"syft:package:foundBy","value":"javascript-lock-cataloger"},{"name":"syft:package:language","value":"javascript"},{"name":"syft:package:type","value":"npm"},{"name":"syft:package:metadataType","value":"javascript-npm-package-lock-entry"},{"name":"syft:cpe23","value":"cpe:2.3:a:\\@actions\\/http-client:\\@actions\\/http_client:1.0.11:*:*:*:*:*:*:*"},{"name":"syft:cpe23","value":"cpe:2.3:a:\\@actions\\/http_client:\\@actions\\/http-client:1.0.11:*:*:*:*:*:*:*"},{"name":"syft:cpe23","value":"cpe:2.3:a:\\@actions\\/http_client:\\@actions\\/http_client:1.0.11:*:*:*:*:*:*:*"},{"name":"syft:cpe23","value":"cpe:2.3:a:\\@actions\\/http:\\@actions\\/http-client:1.0.11:*:*:*:*:*:*:*"},{"name":"syft:cpe23","value":"cpe:2.3:a:\\@actions\\/http:\\@actions\\/http_client:1.0.11:*:*:*:*:*:*:*"},{"name":"syft:location:0:path","value":"\\package-lock.json"}]},{"bom-ref":"pkg:npm/%40notionhq/client@1.0.4?package-id=fa33057fbbf359d8","type":"library","name":"@notionhq/client","version":"1.0.4","cpe":"cpe:2.3:a:\\@notionhq\\/client:\\@notionhq\\/client:1.0.4:*:*:*:*:*:*:*","purl":"pkg:npm/%40notionhq/client@1.0.4","properties":[{"name":"syft:package:foundBy","value":"javascript-lock-cataloger"},{"name":"syft:package:language","value":"javascript"},{"name":"syft:package:type","value":"npm"},{"name":"syft:package:metadataType","value":"javascript-npm-package-lock-entry"},{"name":"syft:location:0:path","value":"\\package-lock.json"}]},{"bom-ref":"pkg:npm/%40octokit/auth-token@2.5.0?package-id=d6b65ae8fea1d86a","type":"library","name":"@octokit/auth-token","version":"2.5.0","cpe":"cpe:2.3:a:\\@octokit\\/auth-token:\\@octokit\\/auth-token:2.5.0:*:*:*:*:*:*:*","purl":"pkg:npm/%40octokit/auth-token@2.5.0","properties":[{"name":"syft:package:foundBy","value":"javascript-lock-cataloger"},{"name":"syft:package:language","value":"javascript"},{"name":"syft:package:type","value":"npm"},{"name":"syft:package:metadataType","value":"javascript-npm-package-lock-entry"},{"name":"syft:cpe23","value":"cpe:2.3:a:\\@octokit\\/auth-token:\\@octokit\\/auth_token:2.5.0:*:*:*:*:*:*:*"},{"name":"syft:cpe23","value":"cpe:2.3:a:\\@octokit\\/auth_token:\\@octokit\\/auth-token:2.5.0:*:*:*:*:*:*:*"},{"name":"syft:cpe23","value":"cpe:2.3:a:\\@octokit\\/auth_token:\\@octokit\\/auth_token:2.5.0:*:*:*:*:*:*:*"},{"name":"syft:cpe23","value":"cpe:2.3:a:\\@octokit\\/auth:\\@octokit\\/auth-token:2.5.0:*:*:*:*:*:*:*"},{"name":"syft:cpe23","value":"cpe:2.3:a:\\@octokit\\/auth:\\@octokit\\/auth_token:2.5.0:*:*:*:*:*:*:*"},{"name":"syft:location:0:path","value":"\\package-lock.json"}]},{"bom-ref":"pkg:npm/%40octokit/core@3.6.0?package-id=44b40ffa4c3d7c88","type":"library","name":"@octokit/core","version":"3.6.0","cpe":"cpe:2.3:a:\\@octokit\\/core:\\@octokit\\/core:3.6.0:*:*:*:*:*:*:*","purl":"pkg:npm/%40octokit/core@3.6.0","properties":[{"name":"syft:package:foundBy","value":"javascript-lock-cataloger"},{"name":"syft:package:language","value":"javascript"},{"name":"syft:package:type","value":"npm"},{"name":"syft:package:metadataType","value":"javascript-npm-package-lock-entry"},{"name":"syft:location:0:path","value":"\\package-lock.json"}]},{"bom-ref":"pkg:npm/%40octokit/endpoint@6.0.12?package-id=a9bcf9d5c32ba5d7","type":"library","name":"@octokit/endpoint","version":"6.0.12","cpe":"cpe:2.3:a:\\@octokit\\/endpoint:\\@octokit\\/endpoint:6.0.12:*:*:*:*:*:*:*","purl":"pkg:npm/%40octokit/endpoint@6.0.12","properties":[{"name":"syft:package:foundBy","value":"javascript-lock-cataloger"},{"name":"syft:package:language","value":"javascript"},{"name":"syft:package:type","value":"npm"},{"name":"syft:package:metadataType","value":"javascript-npm-package-lock-entry"},{"name":"syft:location:0:path","value":"\\package-lock.json"}]},{"bom-ref":"pkg:npm/%40octokit/graphql@4.8.0?package-id=ed1e8db3bc55e612","type":"library","name":"@octokit/graphql","version":"4.8.0","cpe":"cpe:2.3:a:\\@octokit\\/graphql:\\@octokit\\/graphql:4.8.0:*:*:*:*:*:*:*","purl":"pkg:npm/%40octokit/graphql@4.8.0","properties":[{"name":"syft:package:foundBy","value":"javascript-lock-cataloger"},{"name":"syft:package:language","value":"javascript"},{"name":"syft:package:type","value":"npm"},{"name":"syft:package:metadataType","value":"javascript-npm-package-lock-entry"},{"name":"syft:location:0:path","value":"\\package-lock.json"}]},{"bom-ref":"pkg:npm/%40octokit/openapi-types@11.2.0?package-id=38c62fc55a697b96","type":"library","name":"@octokit/openapi-types","version":"11.2.0","cpe":"cpe:2.3:a:\\@octokit\\/openapi-types:\\@octokit\\/openapi-types:11.2.0:*:*:*:*:*:*:*","purl":"pkg:npm/%40octokit/openapi-types@11.2.0","properties":[{"name":"syft:package:foundBy","value":"javascript-lock-cataloger"},{"name":"syft:package:language","value":"javascript"},{"name":"syft:package:type","value":"npm"},{"name":"syft:package:metadataType","value":"javascript-npm-package-lock-entry"},{"name":"syft:cpe23","value":"cpe:2.3:a:\\@octokit\\/openapi-types:\\@octokit\\/openapi_types:11.2.0:*:*:*:*:*:*:*"},{"name":"syft:cpe23","value":"cpe:2.3:a:\\@octokit\\/openapi_types:\\@octokit\\/openapi-types:11.2.0:*:*:*:*:*:*:*"},{"name":"syft:cpe23","value":"cpe:2.3:a:\\@octokit\\/openapi_types:\\@octokit\\/openapi_types:11.2.0:*:*:*:*:*:*:*"},{"name":"syft:cpe23","value":"cpe:2.3:a:\\@octokit\\/openapi:\\@octokit\\/openapi-types:11.2.0:*:*:*:*:*:*:*"},{"name":"syft:cpe23","value":"cpe:2.3:a:\\@octokit\\/openapi:\\@octokit\\/openapi_types:11.2.0:*:*:*:*:*:*:*"},{"name":"syft:location:0:path","value":"\\package-lock.json"}]},{"bom-ref":"pkg:npm/%40octokit/plugin-paginate-rest@2.17.0?package-id=f9f48fbafcc8fec2","type":"library","name":"@octokit/plugin-paginate-rest","version":"2.17.0","cpe":"cpe:2.3:a:\\@octokit\\/plugin-paginate-rest:\\@octokit\\/plugin-paginate-rest:2.17.0:*:*:*:*:*:*:*","purl":"pkg:npm/%40octokit/plugin-paginate-rest@2.17.0","properties":[{"name":"syft:package:foundBy","value":"javascript-lock-cataloger"},{"name":"syft:package:language","value":"javascript"},{"name":"syft:package:type","value":"npm"},{"name":"syft:package:metadataType","value":"javascript-npm-package-lock-entry"},{"name":"syft:cpe23","value":"cpe:2.3:a:\\@octokit\\/plugin-paginate-rest:\\@octokit\\/plugin_paginate_rest:2.17.0:*:*:*:*:*:*:*"},{"name":"syft:cpe23","value":"cpe:2.3:a:\\@octokit\\/plugin_paginate_rest:\\@octokit\\/plugin-paginate-rest:2.17.0:*:*:*:*:*:*:*"},{"name":"syft:cpe23","value":"cpe:2.3:a:\\@octokit\\/plugin_paginate_rest:\\@octokit\\/plugin_paginate_rest:2.17.0:*:*:*:*:*:*:*"},{"name":"syft:cpe23","value":"cpe:2.3:a:\\@octokit\\/plugin-paginate:\\@octokit\\/plugin-paginate-rest:2.17.0:*:*:*:*:*:*:*"},{"name":"syft:cpe23","value":"cpe:2.3:a:\\@octokit\\/plugin-paginate:\\@octokit\\/plugin_paginate_rest:2.17.0:*:*:*:*:*:*:*"},{"name":"syft:cpe23","value":"cpe:2.3:a:\\@octokit\\/plugin_paginate:\\@octokit\\/plugin-paginate-rest:2.17.0:*:*:*:*:*:*:*"},{"name":"syft:cpe23","value":"cpe:2.3:a:\\@octokit\\/plugin_paginate:\\@octokit\\/plugin_paginate_rest:2.17.0:*:*:*:*:*:*:*"},{"name":"syft:cpe23","value":"cpe:2.3:a:\\@octokit\\/plugin:\\@octokit\\/plugin-paginate-rest:2.17.0:*:*:*:*:*:*:*"},{"name":"syft:cpe23","value":"cpe:2.3:a:\\@octokit\\/plugin:\\@octokit\\/plugin_paginate_rest:2.17.0:*:*:*:*:*:*:*"},{"name":"syft:location:0:path","value":"\\package-lock.json"}]},{"bom-ref":"pkg:npm/%40octokit/plugin-rest-endpoint-methods@5.13.0?package-id=3f886d7b8ee1c388","type":"library","name":"@octokit/plugin-rest-endpoint-methods","version":"5.13.0","cpe":"cpe:2.3:a:\\@octokit\\/plugin-rest-endpoint-methods:\\@octokit\\/plugin-rest-endpoint-methods:5.13.0:*:*:*:*:*:*:*","purl":"pkg:npm/%40octokit/plugin-rest-endpoint-methods@5.13.0","properties":[{"name":"syft:package:foundBy","value":"javascript-lock-cataloger"},{"name":"syft:package:language","value":"javascript"},{"name":"syft:package:type","value":"npm"},{"name":"syft:package:metadataType","value":"javascript-npm-package-lock-entry"},{"name":"syft:cpe23","value":"cpe:2.3:a:\\@octokit\\/plugin-rest-endpoint-methods:\\@octokit\\/plugin_rest_endpoint_methods:5.13.0:*:*:*:*:*:*:*"},{"name":"syft:cpe23","value":"cpe:2.3:a:\\@octokit\\/plugin_rest_endpoint_methods:\\@octokit\\/plugin-rest-endpoint-methods:5.13.0:*:*:*:*:*:*:*"},{"name":"syft:cpe23","value":"cpe:2.3:a:\\@octokit\\/plugin_rest_endpoint_methods:\\@octokit\\/plugin_rest_endpoint_methods:5.13.0:*:*:*:*:*:*:*"},{"name":"syft:cpe23","value":"cpe:2.3:a:\\@octokit\\/plugin-rest-endpoint:\\@octokit\\/plugin-rest-endpoint-methods:5.13.0:*:*:*:*:*:*:*"},{"name":"syft:cpe23","value":"cpe:2.3:a:\\@octokit\\/plugin-rest-endpoint:\\@octokit\\/plugin_rest_endpoint_methods:5.13.0:*:*:*:*:*:*:*"},{"name":"syft:cpe23","value":"cpe:2.3:a:\\@octokit\\/plugin_rest_endpoint:\\@octokit\\/plugin-rest-endpoint-methods:5.13.0:*:*:*:*:*:*:*"},{"name":"syft:cpe23","value":"cpe:2.3:a:\\@octokit\\/plugin_rest_endpoint:\\@octokit\\/plugin_rest_endpoint_methods:5.13.0:*:*:*:*:*:*:*"},{"name":"syft:cpe23","value":"cpe:2.3:a:\\@octokit\\/plugin-rest:\\@octokit\\/plugin-rest-endpoint-methods:5.13.0:*:*:*:*:*:*:*"},{"name":"syft:cpe23","value":"cpe:2.3:a:\\@octokit\\/plugin-rest:\\@octokit\\/plugin_rest_endpoint_methods:5.13.0:*:*:*:*:*:*:*"},{"name":"syft:cpe23","value":"cpe:2.3:a:\\@octokit\\/plugin_rest:\\@octokit\\/plugin-rest-endpoint-methods:5.13.0:*:*:*:*:*:*:*"},{"name":"syft:cpe23","value":"cpe:2.3:a:\\@octokit\\/plugin_rest:\\@octokit\\/plugin_rest_endpoint_methods:5.13.0:*:*:*:*:*:*:*"},{"name":"syft:cpe23","value":"cpe:2.3:a:\\@octokit\\/plugin:\\@octokit\\/plugin-rest-endpoint-methods:5.13.0:*:*:*:*:*:*:*"},{"name":"syft:cpe23","value":"cpe:2.3:a:\\@octokit\\/plugin:\\@octokit\\/plugin_rest_endpoint_methods:5.13.0:*:*:*:*:*:*:*"},{"name":"syft:location:0:path","value":"\\package-lock.json"}]},{"bom-ref":"pkg:npm/%40octokit/request@5.6.3?package-id=23e85158f6d379a0","type":"library","name":"@octokit/request","version":"5.6.3","cpe":"cpe:2.3:a:\\@octokit\\/request:\\@octokit\\/request:5.6.3:*:*:*:*:*:*:*","purl":"pkg:npm/%40octokit/request@5.6.3","properties":[{"name":"syft:package:foundBy","value":"javascript-lock-cataloger"},{"name":"syft:package:language","value":"javascript"},{"name":"syft:package:type","value":"npm"},{"name":"syft:package:metadataType","value":"javascript-npm-package-lock-entry"},{"name":"syft:location:0:path","value":"\\package-lock.json"}]},{"bom-ref":"pkg:npm/%40octokit/request-error@2.1.0?package-id=e1680012ac826a10","type":"library","name":"@octokit/request-error","version":"2.1.0","cpe":"cpe:2.3:a:\\@octokit\\/request-error:\\@octokit\\/request-error:2.1.0:*:*:*:*:*:*:*","purl":"pkg:npm/%40octokit/request-error@2.1.0","properties":[{"name":"syft:package:foundBy","value":"javascript-lock-cataloger"},{"name":"syft:package:language","value":"javascript"},{"name":"syft:package:type","value":"npm"},{"name":"syft:package:metadataType","value":"javascript-npm-package-lock-entry"},{"name":"syft:cpe23","value":"cpe:2.3:a:\\@octokit\\/request-error:\\@octokit\\/request_error:2.1.0:*:*:*:*:*:*:*"},{"name":"syft:cpe23","value":"cpe:2.3:a:\\@octokit\\/request_error:\\@octokit\\/request-error:2.1.0:*:*:*:*:*:*:*"},{"name":"syft:cpe23","value":"cpe:2.3:a:\\@octokit\\/request_error:\\@octokit\\/request_error:2.1.0:*:*:*:*:*:*:*"},{"name":"syft:cpe23","value":"cpe:2.3:a:\\@octokit\\/request:\\@octokit\\/request-error:2.1.0:*:*:*:*:*:*:*"},{"name":"syft:cpe23","value":"cpe:2.3:a:\\@octokit\\/request:\\@octokit\\/request_error:2.1.0:*:*:*:*:*:*:*"},{"name":"syft:location:0:path","value":"\\package-lock.json"}]},{"bom-ref":"pkg:npm/%40octokit/types@6.34.0?package-id=9ea4249b9c05e869","type":"library","name":"@octokit/types","version":"6.34.0","cpe":"cpe:2.3:a:\\@octokit\\/types:\\@octokit\\/types:6.34.0:*:*:*:*:*:*:*","purl":"pkg:npm/%40octokit/types@6.34.0","properties":[{"name":"syft:package:foundBy","value":"javascript-lock-cataloger"},{"name":"syft:package:language","value":"javascript"},{"name":"syft:package:type","value":"npm"},{"name":"syft:package:metadataType","value":"javascript-npm-package-lock-entry"},{"name":"syft:location:0:path","value":"\\package-lock.json"}]},{"bom-ref":"pkg:npm/%40types/node@17.0.23?package-id=d1d2f85e3ac89b8a","type":"library","name":"@types/node","version":"17.0.23","cpe":"cpe:2.3:a:\\@types\\/node:\\@types\\/node:17.0.23:*:*:*:*:*:*:*","purl":"pkg:npm/%40types/node@17.0.23","properties":[{"name":"syft:package:foundBy","value":"javascript-lock-cataloger"},{"name":"syft:package:language","value":"javascript"},{"name":"syft:package:type","value":"npm"},{"name":"syft:package:metadataType","value":"javascript-npm-package-lock-entry"},{"name":"syft:location:0:path","value":"\\package-lock.json"}]},{"bom-ref":"pkg:npm/%40types/node-fetch@2.6.1?package-id=8ff906e2c192ae12","type":"library","name":"@types/node-fetch","version":"2.6.1","cpe":"cpe:2.3:a:\\@types\\/node-fetch:\\@types\\/node-fetch:2.6.1:*:*:*:*:*:*:*","purl":"pkg:npm/%40types/node-fetch@2.6.1","properties":[{"name":"syft:package:foundBy","value":"javascript-lock-cataloger"},{"name":"syft:package:language","value":"javascript"},{"name":"syft:package:type","value":"npm"},{"name":"syft:package:metadataType","value":"javascript-npm-package-lock-entry"},{"name":"syft:cpe23","value":"cpe:2.3:a:\\@types\\/node-fetch:\\@types\\/node_fetch:2.6.1:*:*:*:*:*:*:*"},{"name":"syft:cpe23","value":"cpe:2.3:a:\\@types\\/node_fetch:\\@types\\/node-fetch:2.6.1:*:*:*:*:*:*:*"},{"name":"syft:cpe23","value":"cpe:2.3:a:\\@types\\/node_fetch:\\@types\\/node_fetch:2.6.1:*:*:*:*:*:*:*"},{"name":"syft:cpe23","value":"cpe:2.3:a:\\@types\\/node:\\@types\\/node-fetch:2.6.1:*:*:*:*:*:*:*"},{"name":"syft:cpe23","value":"cpe:2.3:a:\\@types\\/node:\\@types\\/node_fetch:2.6.1:*:*:*:*:*:*:*"},{"name":"syft:location:0:path","value":"\\package-lock.json"}]},{"bom-ref":"pkg:github/actions/checkout@v2?package-id=b332ab0b74ae31c2","type":"library","name":"actions/checkout","version":"v2","cpe":"cpe:2.3:a:actions\\/checkout:actions\\/checkout:v2:*:*:*:*:*:*:*","purl":"pkg:github/actions/checkout@v2","properties":[{"name":"syft:package:foundBy","value":"github-actions-usage-cataloger"},{"name":"syft:package:type","value":"github-action"},{"name":"syft:location:0:path","value":"\\.github\\workflows\\on_master.yml"}]},{"bom-ref":"pkg:github/actions/checkout@v2?package-id=40f13e1108d6dd8c","type":"library","name":"actions/checkout","version":"v2","cpe":"cpe:2.3:a:actions\\/checkout:actions\\/checkout:v2:*:*:*:*:*:*:*","purl":"pkg:github/actions/checkout@v2","properties":[{"name":"syft:package:foundBy","value":"github-actions-usage-cataloger"},{"name":"syft:package:type","value":"github-action"},{"name":"syft:location:0:path","value":"\\.github\\workflows\\on_pull_request_open.yml"}]},{"bom-ref":"pkg:github/actions/checkout@v2?package-id=c5e4c2ef85017db7","type":"library","name":"actions/checkout","version":"v2","cpe":"cpe:2.3:a:actions\\/checkout:actions\\/checkout:v2:*:*:*:*:*:*:*","purl":"pkg:github/actions/checkout@v2","properties":[{"name":"syft:package:foundBy","value":"github-actions-usage-cataloger"},{"name":"syft:package:type","value":"github-action"},{"name":"syft:location:0:path","value":"\\.github\\workflows\\sprint_daily.yml"}]},{"bom-ref":"pkg:github/actions/checkout@v2?package-id=45b0183af8b8ce01","type":"library","name":"actions/checkout","version":"v2","cpe":"cpe:2.3:a:actions\\/checkout:actions\\/checkout:v2:*:*:*:*:*:*:*","purl":"pkg:github/actions/checkout@v2","properties":[{"name":"syft:package:foundBy","value":"github-actions-usage-cataloger"},{"name":"syft:package:type","value":"github-action"},{"name":"syft:location:0:path","value":"\\.github\\workflows\\sprint_daily_manual.yml"}]},{"bom-ref":"pkg:github/actions/checkout@v2?package-id=c89d7f2af7c42b8f","type":"library","name":"actions/checkout","version":"v2","cpe":"cpe:2.3:a:actions\\/checkout:actions\\/checkout:v2:*:*:*:*:*:*:*","purl":"pkg:github/actions/checkout@v2","properties":[{"name":"syft:package:foundBy","value":"github-actions-usage-cataloger"},{"name":"syft:package:type","value":"github-action"},{"name":"syft:location:0:path","value":"\\.github\\workflows\\sprint_start.yml"}]},{"bom-ref":"pkg:github/actions/checkout@v2?package-id=8e1ee77a4b4f8e5f","type":"library","name":"actions/checkout","version":"v2","cpe":"cpe:2.3:a:actions\\/checkout:actions\\/checkout:v2:*:*:*:*:*:*:*","purl":"pkg:github/actions/checkout@v2","properties":[{"name":"syft:package:foundBy","value":"github-actions-usage-cataloger"},{"name":"syft:package:type","value":"github-action"},{"name":"syft:location:0:path","value":"\\.github\\workflows\\sprint_start_manual.yml"}]},{"bom-ref":"pkg:github/ad-m/github-push-action@master?package-id=c0bc4ebb16184b97","type":"library","name":"ad-m/github-push-action","version":"master","cpe":"cpe:2.3:a:ad-m\\/github-push-action:ad-m\\/github-push-action:master:*:*:*:*:*:*:*","purl":"pkg:github/ad-m/github-push-action@master","properties":[{"name":"syft:package:foundBy","value":"github-actions-usage-cataloger"},{"name":"syft:package:type","value":"github-action"},{"name":"syft:cpe23","value":"cpe:2.3:a:ad-m\\/github-push-action:ad_m\\/github_push_action:master:*:*:*:*:*:*:*"},{"name":"syft:cpe23","value":"cpe:2.3:a:ad_m\\/github_push_action:ad-m\\/github-push-action:master:*:*:*:*:*:*:*"},{"name":"syft:cpe23","value":"cpe:2.3:a:ad_m\\/github_push_action:ad_m\\/github_push_action:master:*:*:*:*:*:*:*"},{"name":"syft:cpe23","value":"cpe:2.3:a:ad-m\\/github-push:ad-m\\/github-push-action:master:*:*:*:*:*:*:*"},{"name":"syft:cpe23","value":"cpe:2.3:a:ad-m\\/github-push:ad_m\\/github_push_action:master:*:*:*:*:*:*:*"},{"name":"syft:cpe23","value":"cpe:2.3:a:ad_m\\/github_push:ad-m\\/github-push-action:master:*:*:*:*:*:*:*"},{"name":"syft:cpe23","value":"cpe:2.3:a:ad_m\\/github_push:ad_m\\/github_push_action:master:*:*:*:*:*:*:*"},{"name":"syft:cpe23","value":"cpe:2.3:a:ad-m\\/github:ad-m\\/github-push-action:master:*:*:*:*:*:*:*"},{"name":"syft:cpe23","value":"cpe:2.3:a:ad-m\\/github:ad_m\\/github_push_action:master:*:*:*:*:*:*:*"},{"name":"syft:cpe23","value":"cpe:2.3:a:ad_m\\/github:ad-m\\/github-push-action:master:*:*:*:*:*:*:*"},{"name":"syft:cpe23","value":"cpe:2.3:a:ad_m\\/github:ad_m\\/github_push_action:master:*:*:*:*:*:*:*"},{"name":"syft:cpe23","value":"cpe:2.3:a:ad:ad-m\\/github-push-action:master:*:*:*:*:*:*:*"},{"name":"syft:cpe23","value":"cpe:2.3:a:ad:ad_m\\/github_push_action:master:*:*:*:*:*:*:*"},{"name":"syft:location:0:path","value":"\\.github\\workflows\\on_master.yml"}]},{"bom-ref":"pkg:github/ad-m/github-push-action@master?package-id=2c9eb20fb63274fa","type":"library","name":"ad-m/github-push-action","version":"master","cpe":"cpe:2.3:a:ad-m\\/github-push-action:ad-m\\/github-push-action:master:*:*:*:*:*:*:*","purl":"pkg:github/ad-m/github-push-action@master","properties":[{"name":"syft:package:foundBy","value":"github-actions-usage-cataloger"},{"name":"syft:package:type","value":"github-action"},{"name":"syft:cpe23","value":"cpe:2.3:a:ad-m\\/github-push-action:ad_m\\/github_push_action:master:*:*:*:*:*:*:*"},{"name":"syft:cpe23","value":"cpe:2.3:a:ad_m\\/github_push_action:ad-m\\/github-push-action:master:*:*:*:*:*:*:*"},{"name":"syft:cpe23","value":"cpe:2.3:a:ad_m\\/github_push_action:ad_m\\/github_push_action:master:*:*:*:*:*:*:*"},{"name":"syft:cpe23","value":"cpe:2.3:a:ad-m\\/github-push:ad-m\\/github-push-action:master:*:*:*:*:*:*:*"},{"name":"syft:cpe23","value":"cpe:2.3:a:ad-m\\/github-push:ad_m\\/github_push_action:master:*:*:*:*:*:*:*"},{"name":"syft:cpe23","value":"cpe:2.3:a:ad_m\\/github_push:ad-m\\/github-push-action:master:*:*:*:*:*:*:*"},{"name":"syft:cpe23","value":"cpe:2.3:a:ad_m\\/github_push:ad_m\\/github_push_action:master:*:*:*:*:*:*:*"},{"name":"syft:cpe23","value":"cpe:2.3:a:ad-m\\/github:ad-m\\/github-push-action:master:*:*:*:*:*:*:*"},{"name":"syft:cpe23","value":"cpe:2.3:a:ad-m\\/github:ad_m\\/github_push_action:master:*:*:*:*:*:*:*"},{"name":"syft:cpe23","value":"cpe:2.3:a:ad_m\\/github:ad-m\\/github-push-action:master:*:*:*:*:*:*:*"},{"name":"syft:cpe23","value":"cpe:2.3:a:ad_m\\/github:ad_m\\/github_push_action:master:*:*:*:*:*:*:*"},{"name":"syft:cpe23","value":"cpe:2.3:a:ad:ad-m\\/github-push-action:master:*:*:*:*:*:*:*"},{"name":"syft:cpe23","value":"cpe:2.3:a:ad:ad_m\\/github_push_action:master:*:*:*:*:*:*:*"},{"name":"syft:location:0:path","value":"\\.github\\workflows\\sprint_daily.yml"}]},{"bom-ref":"pkg:github/ad-m/github-push-action@master?package-id=0194f27a236c97fd","type":"library","name":"ad-m/github-push-action","version":"master","cpe":"cpe:2.3:a:ad-m\\/github-push-action:ad-m\\/github-push-action:master:*:*:*:*:*:*:*","purl":"pkg:github/ad-m/github-push-action@master","properties":[{"name":"syft:package:foundBy","value":"github-actions-usage-cataloger"},{"name":"syft:package:type","value":"github-action"},{"name":"syft:cpe23","value":"cpe:2.3:a:ad-m\\/github-push-action:ad_m\\/github_push_action:master:*:*:*:*:*:*:*"},{"name":"syft:cpe23","value":"cpe:2.3:a:ad_m\\/github_push_action:ad-m\\/github-push-action:master:*:*:*:*:*:*:*"},{"name":"syft:cpe23","value":"cpe:2.3:a:ad_m\\/github_push_action:ad_m\\/github_push_action:master:*:*:*:*:*:*:*"},{"name":"syft:cpe23","value":"cpe:2.3:a:ad-m\\/github-push:ad-m\\/github-push-action:master:*:*:*:*:*:*:*"},{"name":"syft:cpe23","value":"cpe:2.3:a:ad-m\\/github-push:ad_m\\/github_push_action:master:*:*:*:*:*:*:*"},{"name":"syft:cpe23","value":"cpe:2.3:a:ad_m\\/github_push:ad-m\\/github-push-action:master:*:*:*:*:*:*:*"},{"name":"syft:cpe23","value":"cpe:2.3:a:ad_m\\/github_push:ad_m\\/github_push_action:master:*:*:*:*:*:*:*"},{"name":"syft:cpe23","value":"cpe:2.3:a:ad-m\\/github:ad-m\\/github-push-action:master:*:*:*:*:*:*:*"},{"name":"syft:cpe23","value":"cpe:2.3:a:ad-m\\/github:ad_m\\/github_push_action:master:*:*:*:*:*:*:*"},{"name":"syft:cpe23","value":"cpe:2.3:a:ad_m\\/github:ad-m\\/github-push-action:master:*:*:*:*:*:*:*"},{"name":"syft:cpe23","value":"cpe:2.3:a:ad_m\\/github:ad_m\\/github_push_action:master:*:*:*:*:*:*:*"},{"name":"syft:cpe23","value":"cpe:2.3:a:ad:ad-m\\/github-push-action:master:*:*:*:*:*:*:*"},{"name":"syft:cpe23","value":"cpe:2.3:a:ad:ad_m\\/github_push_action:master:*:*:*:*:*:*:*"},{"name":"syft:location:0:path","value":"\\.github\\workflows\\sprint_daily_manual.yml"}]},{"bom-ref":"pkg:github/ad-m/github-push-action@master?package-id=bd4ebf86a10cb7f7","type":"library","name":"ad-m/github-push-action","version":"master","cpe":"cpe:2.3:a:ad-m\\/github-push-action:ad-m\\/github-push-action:master:*:*:*:*:*:*:*","purl":"pkg:github/ad-m/github-push-action@master","properties":[{"name":"syft:package:foundBy","value":"github-actions-usage-cataloger"},{"name":"syft:package:type","value":"github-action"},{"name":"syft:cpe23","value":"cpe:2.3:a:ad-m\\/github-push-action:ad_m\\/github_push_action:master:*:*:*:*:*:*:*"},{"name":"syft:cpe23","value":"cpe:2.3:a:ad_m\\/github_push_action:ad-m\\/github-push-action:master:*:*:*:*:*:*:*"},{"name":"syft:cpe23","value":"cpe:2.3:a:ad_m\\/github_push_action:ad_m\\/github_push_action:master:*:*:*:*:*:*:*"},{"name":"syft:cpe23","value":"cpe:2.3:a:ad-m\\/github-push:ad-m\\/github-push-action:master:*:*:*:*:*:*:*"},{"name":"syft:cpe23","value":"cpe:2.3:a:ad-m\\/github-push:ad_m\\/github_push_action:master:*:*:*:*:*:*:*"},{"name":"syft:cpe23","value":"cpe:2.3:a:ad_m\\/github_push:ad-m\\/github-push-action:master:*:*:*:*:*:*:*"},{"name":"syft:cpe23","value":"cpe:2.3:a:ad_m\\/github_push:ad_m\\/github_push_action:master:*:*:*:*:*:*:*"},{"name":"syft:cpe23","value":"cpe:2.3:a:ad-m\\/github:ad-m\\/github-push-action:master:*:*:*:*:*:*:*"},{"name":"syft:cpe23","value":"cpe:2.3:a:ad-m\\/github:ad_m\\/github_push_action:master:*:*:*:*:*:*:*"},{"name":"syft:cpe23","value":"cpe:2.3:a:ad_m\\/github:ad-m\\/github-push-action:master:*:*:*:*:*:*:*"},{"name":"syft:cpe23","value":"cpe:2.3:a:ad_m\\/github:ad_m\\/github_push_action:master:*:*:*:*:*:*:*"},{"name":"syft:cpe23","value":"cpe:2.3:a:ad:ad-m\\/github-push-action:master:*:*:*:*:*:*:*"},{"name":"syft:cpe23","value":"cpe:2.3:a:ad:ad_m\\/github_push_action:master:*:*:*:*:*:*:*"},{"name":"syft:location:0:path","value":"\\.github\\workflows\\sprint_start.yml"}]},{"bom-ref":"pkg:github/ad-m/github-push-action@master?package-id=2e5708962ad52c5e","type":"library","name":"ad-m/github-push-action","version":"master","cpe":"cpe:2.3:a:ad-m\\/github-push-action:ad-m\\/github-push-action:master:*:*:*:*:*:*:*","purl":"pkg:github/ad-m/github-push-action@master","properties":[{"name":"syft:package:foundBy","value":"github-actions-usage-cataloger"},{"name":"syft:package:type","value":"github-action"},{"name":"syft:cpe23","value":"cpe:2.3:a:ad-m\\/github-push-action:ad_m\\/github_push_action:master:*:*:*:*:*:*:*"},{"name":"syft:cpe23","value":"cpe:2.3:a:ad_m\\/github_push_action:ad-m\\/github-push-action:master:*:*:*:*:*:*:*"},{"name":"syft:cpe23","value":"cpe:2.3:a:ad_m\\/github_push_action:ad_m\\/github_push_action:master:*:*:*:*:*:*:*"},{"name":"syft:cpe23","value":"cpe:2.3:a:ad-m\\/github-push:ad-m\\/github-push-action:master:*:*:*:*:*:*:*"},{"name":"syft:cpe23","value":"cpe:2.3:a:ad-m\\/github-push:ad_m\\/github_push_action:master:*:*:*:*:*:*:*"},{"name":"syft:cpe23","value":"cpe:2.3:a:ad_m\\/github_push:ad-m\\/github-push-action:master:*:*:*:*:*:*:*"},{"name":"syft:cpe23","value":"cpe:2.3:a:ad_m\\/github_push:ad_m\\/github_push_action:master:*:*:*:*:*:*:*"},{"name":"syft:cpe23","value":"cpe:2.3:a:ad-m\\/github:ad-m\\/github-push-action:master:*:*:*:*:*:*:*"},{"name":"syft:cpe23","value":"cpe:2.3:a:ad-m\\/github:ad_m\\/github_push_action:master:*:*:*:*:*:*:*"},{"name":"syft:cpe23","value":"cpe:2.3:a:ad_m\\/github:ad-m\\/github-push-action:master:*:*:*:*:*:*:*"},{"name":"syft:cpe23","value":"cpe:2.3:a:ad_m\\/github:ad_m\\/github_push_action:master:*:*:*:*:*:*:*"},{"name":"syft:cpe23","value":"cpe:2.3:a:ad:ad-m\\/github-push-action:master:*:*:*:*:*:*:*"},{"name":"syft:cpe23","value":"cpe:2.3:a:ad:ad_m\\/github_push_action:master:*:*:*:*:*:*:*"},{"name":"syft:location:0:path","value":"\\.github\\workflows\\sprint_start_manual.yml"}]},{"bom-ref":"pkg:github/anothrnick/github-tag-action@1.36.0?package-id=5d4fcb7ecfb21894","type":"library","name":"anothrNick/github-tag-action","version":"1.36.0","cpe":"cpe:2.3:a:anothrNick\\/github-tag-action:anothrNick\\/github-tag-action:1.36.0:*:*:*:*:*:*:*","purl":"pkg:github/anothrNick/github-tag-action@1.36.0","properties":[{"name":"syft:package:foundBy","value":"github-actions-usage-cataloger"},{"name":"syft:package:type","value":"github-action"},{"name":"syft:cpe23","value":"cpe:2.3:a:anothrNick\\/github-tag-action:anothrNick\\/github_tag_action:1.36.0:*:*:*:*:*:*:*"},{"name":"syft:cpe23","value":"cpe:2.3:a:anothrNick\\/github_tag_action:anothrNick\\/github-tag-action:1.36.0:*:*:*:*:*:*:*"},{"name":"syft:cpe23","value":"cpe:2.3:a:anothrNick\\/github_tag_action:anothrNick\\/github_tag_action:1.36.0:*:*:*:*:*:*:*"},{"name":"syft:cpe23","value":"cpe:2.3:a:anothrNick\\/github-tag:anothrNick\\/github-tag-action:1.36.0:*:*:*:*:*:*:*"},{"name":"syft:cpe23","value":"cpe:2.3:a:anothrNick\\/github-tag:anothrNick\\/github_tag_action:1.36.0:*:*:*:*:*:*:*"},{"name":"syft:cpe23","value":"cpe:2.3:a:anothrNick\\/github_tag:anothrNick\\/github-tag-action:1.36.0:*:*:*:*:*:*:*"},{"name":"syft:cpe23","value":"cpe:2.3:a:anothrNick\\/github_tag:anothrNick\\/github_tag_action:1.36.0:*:*:*:*:*:*:*"},{"name":"syft:cpe23","value":"cpe:2.3:a:anothrNick\\/github:anothrNick\\/github-tag-action:1.36.0:*:*:*:*:*:*:*"},{"name":"syft:cpe23","value":"cpe:2.3:a:anothrNick\\/github:anothrNick\\/github_tag_action:1.36.0:*:*:*:*:*:*:*"},{"name":"syft:location:0:path","value":"\\.github\\workflows\\on_master.yml"}]},{"bom-ref":"pkg:npm/asynckit@0.4.0?package-id=a1904d009a98021e","type":"library","name":"asynckit","version":"0.4.0","cpe":"cpe:2.3:a:asynckit:asynckit:0.4.0:*:*:*:*:*:*:*","purl":"pkg:npm/asynckit@0.4.0","properties":[{"name":"syft:package:foundBy","value":"javascript-lock-cataloger"},{"name":"syft:package:language","value":"javascript"},{"name":"syft:package:type","value":"npm"},{"name":"syft:package:metadataType","value":"javascript-npm-package-lock-entry"},{"name":"syft:location:0:path","value":"\\package-lock.json"}]},{"bom-ref":"pkg:npm/before-after-hook@2.2.2?package-id=c91e9fcaebd481b8","type":"library","name":"before-after-hook","version":"2.2.2","cpe":"cpe:2.3:a:before-after-hook:before-after-hook:2.2.2:*:*:*:*:*:*:*","purl":"pkg:npm/before-after-hook@2.2.2","properties":[{"name":"syft:package:foundBy","value":"javascript-lock-cataloger"},{"name":"syft:package:language","value":"javascript"},{"name":"syft:package:type","value":"npm"},{"name":"syft:package:metadataType","value":"javascript-npm-package-lock-entry"},{"name":"syft:cpe23","value":"cpe:2.3:a:before-after-hook:before_after_hook:2.2.2:*:*:*:*:*:*:*"},{"name":"syft:cpe23","value":"cpe:2.3:a:before_after_hook:before-after-hook:2.2.2:*:*:*:*:*:*:*"},{"name":"syft:cpe23","value":"cpe:2.3:a:before_after_hook:before_after_hook:2.2.2:*:*:*:*:*:*:*"},{"name":"syft:cpe23","value":"cpe:2.3:a:before-after:before-after-hook:2.2.2:*:*:*:*:*:*:*"},{"name":"syft:cpe23","value":"cpe:2.3:a:before-after:before_after_hook:2.2.2:*:*:*:*:*:*:*"},{"name":"syft:cpe23","value":"cpe:2.3:a:before_after:before-after-hook:2.2.2:*:*:*:*:*:*:*"},{"name":"syft:cpe23","value":"cpe:2.3:a:before_after:before_after_hook:2.2.2:*:*:*:*:*:*:*"},{"name":"syft:cpe23","value":"cpe:2.3:a:before:before-after-hook:2.2.2:*:*:*:*:*:*:*"},{"name":"syft:cpe23","value":"cpe:2.3:a:before:before_after_hook:2.2.2:*:*:*:*:*:*:*"},{"name":"syft:location:0:path","value":"\\package-lock.json"}]},{"bom-ref":"pkg:npm/chart.js-image@6.0.3?package-id=784476a72913c228","type":"library","name":"chart.js-image","version":"6.0.3","cpe":"cpe:2.3:a:chart.js-image:chart.js-image:6.0.3:*:*:*:*:*:*:*","purl":"pkg:npm/chart.js-image@6.0.3","properties":[{"name":"syft:package:foundBy","value":"javascript-lock-cataloger"},{"name":"syft:package:language","value":"javascript"},{"name":"syft:package:type","value":"npm"},{"name":"syft:package:metadataType","value":"javascript-npm-package-lock-entry"},{"name":"syft:cpe23","value":"cpe:2.3:a:chart.js-image:chart.js_image:6.0.3:*:*:*:*:*:*:*"},{"name":"syft:cpe23","value":"cpe:2.3:a:chart.js_image:chart.js-image:6.0.3:*:*:*:*:*:*:*"},{"name":"syft:cpe23","value":"cpe:2.3:a:chart.js_image:chart.js_image:6.0.3:*:*:*:*:*:*:*"},{"name":"syft:cpe23","value":"cpe:2.3:a:chart.js:chart.js-image:6.0.3:*:*:*:*:*:*:*"},{"name":"syft:cpe23","value":"cpe:2.3:a:chart.js:chart.js_image:6.0.3:*:*:*:*:*:*:*"},{"name":"syft:location:0:path","value":"\\package-lock.json"}]},{"bom-ref":"pkg:npm/combined-stream@1.0.8?package-id=000d55011a078ffe","type":"library","name":"combined-stream","version":"1.0.8","cpe":"cpe:2.3:a:combined-stream:combined-stream:1.0.8:*:*:*:*:*:*:*","purl":"pkg:npm/combined-stream@1.0.8","properties":[{"name":"syft:package:foundBy","value":"javascript-lock-cataloger"},{"name":"syft:package:language","value":"javascript"},{"name":"syft:package:type","value":"npm"},{"name":"syft:package:metadataType","value":"javascript-npm-package-lock-entry"},{"name":"syft:cpe23","value":"cpe:2.3:a:combined-stream:combined_stream:1.0.8:*:*:*:*:*:*:*"},{"name":"syft:cpe23","value":"cpe:2.3:a:combined_stream:combined-stream:1.0.8:*:*:*:*:*:*:*"},{"name":"syft:cpe23","value":"cpe:2.3:a:combined_stream:combined_stream:1.0.8:*:*:*:*:*:*:*"},{"name":"syft:cpe23","value":"cpe:2.3:a:combined:combined-stream:1.0.8:*:*:*:*:*:*:*"},{"name":"syft:cpe23","value":"cpe:2.3:a:combined:combined_stream:1.0.8:*:*:*:*:*:*:*"},{"name":"syft:location:0:path","value":"\\package-lock.json"}]},{"bom-ref":"pkg:npm/delayed-stream@1.0.0?package-id=d2bbef1f4ecfe31d","type":"library","name":"delayed-stream","version":"1.0.0","cpe":"cpe:2.3:a:delayed-stream:delayed-stream:1.0.0:*:*:*:*:*:*:*","purl":"pkg:npm/delayed-stream@1.0.0","properties":[{"name":"syft:package:foundBy","value":"javascript-lock-cataloger"},{"name":"syft:package:language","value":"javascript"},{"name":"syft:package:type","value":"npm"},{"name":"syft:package:metadataType","value":"javascript-npm-package-lock-entry"},{"name":"syft:cpe23","value":"cpe:2.3:a:delayed-stream:delayed_stream:1.0.0:*:*:*:*:*:*:*"},{"name":"syft:cpe23","value":"cpe:2.3:a:delayed_stream:delayed-stream:1.0.0:*:*:*:*:*:*:*"},{"name":"syft:cpe23","value":"cpe:2.3:a:delayed_stream:delayed_stream:1.0.0:*:*:*:*:*:*:*"},{"name":"syft:cpe23","value":"cpe:2.3:a:delayed:delayed-stream:1.0.0:*:*:*:*:*:*:*"},{"name":"syft:cpe23","value":"cpe:2.3:a:delayed:delayed_stream:1.0.0:*:*:*:*:*:*:*"},{"name":"syft:location:0:path","value":"\\package-lock.json"}]},{"bom-ref":"pkg:npm/deprecation@2.3.1?package-id=36e8edcb7d4b6b6c","type":"library","name":"deprecation","version":"2.3.1","cpe":"cpe:2.3:a:deprecation:deprecation:2.3.1:*:*:*:*:*:*:*","purl":"pkg:npm/deprecation@2.3.1","properties":[{"name":"syft:package:foundBy","value":"javascript-lock-cataloger"},{"name":"syft:package:language","value":"javascript"},{"name":"syft:package:type","value":"npm"},{"name":"syft:package:metadataType","value":"javascript-npm-package-lock-entry"},{"name":"syft:location:0:path","value":"\\package-lock.json"}]},{"bom-ref":"pkg:npm/dotenv@16.0.0?package-id=51fc1eecf494faf4","type":"library","name":"dotenv","version":"16.0.0","cpe":"cpe:2.3:a:dotenv:dotenv:16.0.0:*:*:*:*:*:*:*","purl":"pkg:npm/dotenv@16.0.0","properties":[{"name":"syft:package:foundBy","value":"javascript-lock-cataloger"},{"name":"syft:package:language","value":"javascript"},{"name":"syft:package:type","value":"npm"},{"name":"syft:package:metadataType","value":"javascript-npm-package-lock-entry"},{"name":"syft:location:0:path","value":"\\package-lock.json"}]},{"bom-ref":"pkg:npm/form-data@3.0.1?package-id=5a49c2a6db441429","type":"library","name":"form-data","version":"3.0.1","cpe":"cpe:2.3:a:form-data:form-data:3.0.1:*:*:*:*:*:*:*","purl":"pkg:npm/form-data@3.0.1","properties":[{"name":"syft:package:foundBy","value":"javascript-lock-cataloger"},{"name":"syft:package:language","value":"javascript"},{"name":"syft:package:type","value":"npm"},{"name":"syft:package:metadataType","value":"javascript-npm-package-lock-entry"},{"name":"syft:cpe23","value":"cpe:2.3:a:form-data:form_data:3.0.1:*:*:*:*:*:*:*"},{"name":"syft:cpe23","value":"cpe:2.3:a:form_data:form-data:3.0.1:*:*:*:*:*:*:*"},{"name":"syft:cpe23","value":"cpe:2.3:a:form_data:form_data:3.0.1:*:*:*:*:*:*:*"},{"name":"syft:cpe23","value":"cpe:2.3:a:form:form-data:3.0.1:*:*:*:*:*:*:*"},{"name":"syft:cpe23","value":"cpe:2.3:a:form:form_data:3.0.1:*:*:*:*:*:*:*"},{"name":"syft:location:0:path","value":"\\package-lock.json"}]},{"bom-ref":"pkg:npm/is-plain-object@5.0.0?package-id=f8419bcf57837d5d","type":"library","name":"is-plain-object","version":"5.0.0","cpe":"cpe:2.3:a:is-plain-object:is-plain-object:5.0.0:*:*:*:*:*:*:*","purl":"pkg:npm/is-plain-object@5.0.0","properties":[{"name":"syft:package:foundBy","value":"javascript-lock-cataloger"},{"name":"syft:package:language","value":"javascript"},{"name":"syft:package:type","value":"npm"},{"name":"syft:package:metadataType","value":"javascript-npm-package-lock-entry"},{"name":"syft:cpe23","value":"cpe:2.3:a:is-plain-object:is_plain_object:5.0.0:*:*:*:*:*:*:*"},{"name":"syft:cpe23","value":"cpe:2.3:a:is_plain_object:is-plain-object:5.0.0:*:*:*:*:*:*:*"},{"name":"syft:cpe23","value":"cpe:2.3:a:is_plain_object:is_plain_object:5.0.0:*:*:*:*:*:*:*"},{"name":"syft:cpe23","value":"cpe:2.3:a:is-plain:is-plain-object:5.0.0:*:*:*:*:*:*:*"},{"name":"syft:cpe23","value":"cpe:2.3:a:is-plain:is_plain_object:5.0.0:*:*:*:*:*:*:*"},{"name":"syft:cpe23","value":"cpe:2.3:a:is_plain:is-plain-object:5.0.0:*:*:*:*:*:*:*"},{"name":"syft:cpe23","value":"cpe:2.3:a:is_plain:is_plain_object:5.0.0:*:*:*:*:*:*:*"},{"name":"syft:cpe23","value":"cpe:2.3:a:is:is-plain-object:5.0.0:*:*:*:*:*:*:*"},{"name":"syft:cpe23","value":"cpe:2.3:a:is:is_plain_object:5.0.0:*:*:*:*:*:*:*"},{"name":"syft:location:0:path","value":"\\package-lock.json"}]},{"bom-ref":"pkg:npm/javascript-stringify@2.0.1?package-id=2b27412215e2bbb0","type":"library","name":"javascript-stringify","version":"2.0.1","cpe":"cpe:2.3:a:javascript-stringify:javascript-stringify:2.0.1:*:*:*:*:*:*:*","purl":"pkg:npm/javascript-stringify@2.0.1","properties":[{"name":"syft:package:foundBy","value":"javascript-lock-cataloger"},{"name":"syft:package:language","value":"javascript"},{"name":"syft:package:type","value":"npm"},{"name":"syft:package:metadataType","value":"javascript-npm-package-lock-entry"},{"name":"syft:cpe23","value":"cpe:2.3:a:javascript-stringify:javascript_stringify:2.0.1:*:*:*:*:*:*:*"},{"name":"syft:cpe23","value":"cpe:2.3:a:javascript_stringify:javascript-stringify:2.0.1:*:*:*:*:*:*:*"},{"name":"syft:cpe23","value":"cpe:2.3:a:javascript_stringify:javascript_stringify:2.0.1:*:*:*:*:*:*:*"},{"name":"syft:cpe23","value":"cpe:2.3:a:javascript:javascript-stringify:2.0.1:*:*:*:*:*:*:*"},{"name":"syft:cpe23","value":"cpe:2.3:a:javascript:javascript_stringify:2.0.1:*:*:*:*:*:*:*"},{"name":"syft:location:0:path","value":"\\package-lock.json"}]},{"bom-ref":"pkg:npm/lodash@4.17.21?package-id=6e3dea74840b7896","type":"library","name":"lodash","version":"4.17.21","cpe":"cpe:2.3:a:lodash:lodash:4.17.21:*:*:*:*:node.js:*:*","purl":"pkg:npm/lodash@4.17.21","properties":[{"name":"syft:package:foundBy","value":"javascript-lock-cataloger"},{"name":"syft:package:language","value":"javascript"},{"name":"syft:package:type","value":"npm"},{"name":"syft:package:metadataType","value":"javascript-npm-package-lock-entry"},{"name":"syft:location:0:path","value":"\\package-lock.json"}]},{"bom-ref":"pkg:npm/loglevel@1.8.0?package-id=d6b35cc90746469c","type":"library","name":"loglevel","version":"1.8.0","cpe":"cpe:2.3:a:loglevel:loglevel:1.8.0:*:*:*:*:*:*:*","purl":"pkg:npm/loglevel@1.8.0","properties":[{"name":"syft:package:foundBy","value":"javascript-lock-cataloger"},{"name":"syft:package:language","value":"javascript"},{"name":"syft:package:type","value":"npm"},{"name":"syft:package:metadataType","value":"javascript-npm-package-lock-entry"},{"name":"syft:location:0:path","value":"\\package-lock.json"}]},{"bom-ref":"pkg:npm/mime-db@1.52.0?package-id=fb5f2b4fb1104fc2","type":"library","name":"mime-db","version":"1.52.0","cpe":"cpe:2.3:a:mime-db:mime-db:1.52.0:*:*:*:*:*:*:*","purl":"pkg:npm/mime-db@1.52.0","properties":[{"name":"syft:package:foundBy","value":"javascript-lock-cataloger"},{"name":"syft:package:language","value":"javascript"},{"name":"syft:package:type","value":"npm"},{"name":"syft:package:metadataType","value":"javascript-npm-package-lock-entry"},{"name":"syft:cpe23","value":"cpe:2.3:a:mime-db:mime_db:1.52.0:*:*:*:*:*:*:*"},{"name":"syft:cpe23","value":"cpe:2.3:a:mime_db:mime-db:1.52.0:*:*:*:*:*:*:*"},{"name":"syft:cpe23","value":"cpe:2.3:a:mime_db:mime_db:1.52.0:*:*:*:*:*:*:*"},{"name":"syft:cpe23","value":"cpe:2.3:a:mime:mime-db:1.52.0:*:*:*:*:*:*:*"},{"name":"syft:cpe23","value":"cpe:2.3:a:mime:mime_db:1.52.0:*:*:*:*:*:*:*"},{"name":"syft:location:0:path","value":"\\package-lock.json"}]},{"bom-ref":"pkg:npm/mime-types@2.1.35?package-id=86ba993e8d6b8c30","type":"library","name":"mime-types","version":"2.1.35","cpe":"cpe:2.3:a:mime-types:mime-types:2.1.35:*:*:*:*:*:*:*","purl":"pkg:npm/mime-types@2.1.35","properties":[{"name":"syft:package:foundBy","value":"javascript-lock-cataloger"},{"name":"syft:package:language","value":"javascript"},{"name":"syft:package:type","value":"npm"},{"name":"syft:package:metadataType","value":"javascript-npm-package-lock-entry"},{"name":"syft:cpe23","value":"cpe:2.3:a:mime-types:mime_types:2.1.35:*:*:*:*:*:*:*"},{"name":"syft:cpe23","value":"cpe:2.3:a:mime_types:mime-types:2.1.35:*:*:*:*:*:*:*"},{"name":"syft:cpe23","value":"cpe:2.3:a:mime_types:mime_types:2.1.35:*:*:*:*:*:*:*"},{"name":"syft:cpe23","value":"cpe:2.3:a:mime:mime-types:2.1.35:*:*:*:*:*:*:*"},{"name":"syft:cpe23","value":"cpe:2.3:a:mime:mime_types:2.1.35:*:*:*:*:*:*:*"},{"name":"syft:location:0:path","value":"\\package-lock.json"}]},{"bom-ref":"pkg:npm/moment@2.29.2?package-id=67e896a60e92af29","type":"library","name":"moment","version":"2.29.2","cpe":"cpe:2.3:a:momentjs:moment:2.29.2:*:*:*:*:node.js:*:*","purl":"pkg:npm/moment@2.29.2","properties":[{"name":"syft:package:foundBy","value":"javascript-lock-cataloger"},{"name":"syft:package:language","value":"javascript"},{"name":"syft:package:type","value":"npm"},{"name":"syft:package:metadataType","value":"javascript-npm-package-lock-entry"},{"name":"syft:location:0:path","value":"\\package-lock.json"}]},{"bom-ref":"pkg:npm/moment-timezone@0.5.34?package-id=24a5fc0cd3d5e7ba","type":"library","name":"moment-timezone","version":"0.5.34","cpe":"cpe:2.3:a:moment-timezone:moment-timezone:0.5.34:*:*:*:*:*:*:*","purl":"pkg:npm/moment-timezone@0.5.34","properties":[{"name":"syft:package:foundBy","value":"javascript-lock-cataloger"},{"name":"syft:package:language","value":"javascript"},{"name":"syft:package:type","value":"npm"},{"name":"syft:package:metadataType","value":"javascript-npm-package-lock-entry"},{"name":"syft:cpe23","value":"cpe:2.3:a:moment-timezone:moment_timezone:0.5.34:*:*:*:*:*:*:*"},{"name":"syft:cpe23","value":"cpe:2.3:a:moment_timezone:moment-timezone:0.5.34:*:*:*:*:*:*:*"},{"name":"syft:cpe23","value":"cpe:2.3:a:moment_timezone:moment_timezone:0.5.34:*:*:*:*:*:*:*"},{"name":"syft:cpe23","value":"cpe:2.3:a:moment:moment-timezone:0.5.34:*:*:*:*:*:*:*"},{"name":"syft:cpe23","value":"cpe:2.3:a:moment:moment_timezone:0.5.34:*:*:*:*:*:*:*"},{"name":"syft:location:0:path","value":"\\package-lock.json"}]},{"bom-ref":"pkg:npm/node-fetch@2.6.0?package-id=532aadf9ab91bc73","type":"library","name":"node-fetch","version":"2.6.0","cpe":"cpe:2.3:a:node-fetch_project:node-fetch:2.6.0:*:*:*:*:node.js:*:*","purl":"pkg:npm/node-fetch@2.6.0","properties":[{"name":"syft:package:foundBy","value":"javascript-lock-cataloger"},{"name":"syft:package:language","value":"javascript"},{"name":"syft:package:type","value":"npm"},{"name":"syft:package:metadataType","value":"javascript-npm-package-lock-entry"},{"name":"syft:location:0:path","value":"\\package-lock.json"}]},{"bom-ref":"pkg:npm/node-fetch@2.6.7?package-id=424342bf6d6ceb7b","type":"library","name":"node-fetch","version":"2.6.7","cpe":"cpe:2.3:a:node-fetch_project:node-fetch:2.6.7:*:*:*:*:node.js:*:*","purl":"pkg:npm/node-fetch@2.6.7","properties":[{"name":"syft:package:foundBy","value":"javascript-lock-cataloger"},{"name":"syft:package:language","value":"javascript"},{"name":"syft:package:type","value":"npm"},{"name":"syft:package:metadataType","value":"javascript-npm-package-lock-entry"},{"name":"syft:location:0:path","value":"\\package-lock.json"}]},{"bom-ref":"pkg:npm/notion@1.0.0?package-id=c4e7af345b81feb7","type":"library","name":"notion","version":"1.0.0","licenses":[{"license":{"id":"ISC"}}],"cpe":"cpe:2.3:a:notion:notion:1.0.0:*:*:*:*:*:*:*","purl":"pkg:npm/notion@1.0.0","properties":[{"name":"syft:package:foundBy","value":"javascript-lock-cataloger"},{"name":"syft:package:language","value":"javascript"},{"name":"syft:package:type","value":"npm"},{"name":"syft:package:metadataType","value":"javascript-npm-package-lock-entry"},{"name":"syft:location:0:path","value":"\\package-lock.json"}]},{"bom-ref":"pkg:npm/once@1.4.0?package-id=2ddb5e97b2f34736","type":"library","name":"once","version":"1.4.0","cpe":"cpe:2.3:a:once:once:1.4.0:*:*:*:*:*:*:*","purl":"pkg:npm/once@1.4.0","properties":[{"name":"syft:package:foundBy","value":"javascript-lock-cataloger"},{"name":"syft:package:language","value":"javascript"},{"name":"syft:package:type","value":"npm"},{"name":"syft:package:metadataType","value":"javascript-npm-package-lock-entry"},{"name":"syft:location:0:path","value":"\\package-lock.json"}]},{"bom-ref":"pkg:github/szenius/notion-update-page@1.1.12?package-id=fc77c138e7455fb1","type":"library","name":"szenius/notion-update-page","version":"1.1.12","cpe":"cpe:2.3:a:szenius\\/notion-update-page:szenius\\/notion-update-page:1.1.12:*:*:*:*:*:*:*","purl":"pkg:github/szenius/notion-update-page@1.1.12","properties":[{"name":"syft:package:foundBy","value":"github-actions-usage-cataloger"},{"name":"syft:package:type","value":"github-action"},{"name":"syft:cpe23","value":"cpe:2.3:a:szenius\\/notion-update-page:szenius\\/notion_update_page:1.1.12:*:*:*:*:*:*:*"},{"name":"syft:cpe23","value":"cpe:2.3:a:szenius\\/notion_update_page:szenius\\/notion-update-page:1.1.12:*:*:*:*:*:*:*"},{"name":"syft:cpe23","value":"cpe:2.3:a:szenius\\/notion_update_page:szenius\\/notion_update_page:1.1.12:*:*:*:*:*:*:*"},{"name":"syft:cpe23","value":"cpe:2.3:a:szenius\\/notion-update:szenius\\/notion-update-page:1.1.12:*:*:*:*:*:*:*"},{"name":"syft:cpe23","value":"cpe:2.3:a:szenius\\/notion-update:szenius\\/notion_update_page:1.1.12:*:*:*:*:*:*:*"},{"name":"syft:cpe23","value":"cpe:2.3:a:szenius\\/notion_update:szenius\\/notion-update-page:1.1.12:*:*:*:*:*:*:*"},{"name":"syft:cpe23","value":"cpe:2.3:a:szenius\\/notion_update:szenius\\/notion_update_page:1.1.12:*:*:*:*:*:*:*"},{"name":"syft:cpe23","value":"cpe:2.3:a:szenius\\/notion:szenius\\/notion-update-page:1.1.12:*:*:*:*:*:*:*"},{"name":"syft:cpe23","value":"cpe:2.3:a:szenius\\/notion:szenius\\/notion_update_page:1.1.12:*:*:*:*:*:*:*"},{"name":"syft:location:0:path","value":"\\.github\\workflows\\on_master.yml"}]},{"bom-ref":"pkg:npm/tr46@0.0.3?package-id=1a296b646dd7ad30","type":"library","name":"tr46","version":"0.0.3","cpe":"cpe:2.3:a:tr46:tr46:0.0.3:*:*:*:*:*:*:*","purl":"pkg:npm/tr46@0.0.3","properties":[{"name":"syft:package:foundBy","value":"javascript-lock-cataloger"},{"name":"syft:package:language","value":"javascript"},{"name":"syft:package:type","value":"npm"},{"name":"syft:package:metadataType","value":"javascript-npm-package-lock-entry"},{"name":"syft:location:0:path","value":"\\package-lock.json"}]},{"bom-ref":"pkg:npm/tunnel@0.0.6?package-id=a85ba2e784e15009","type":"library","name":"tunnel","version":"0.0.6","cpe":"cpe:2.3:a:tunnel:tunnel:0.0.6:*:*:*:*:*:*:*","purl":"pkg:npm/tunnel@0.0.6","properties":[{"name":"syft:package:foundBy","value":"javascript-lock-cataloger"},{"name":"syft:package:language","value":"javascript"},{"name":"syft:package:type","value":"npm"},{"name":"syft:package:metadataType","value":"javascript-npm-package-lock-entry"},{"name":"syft:location:0:path","value":"\\package-lock.json"}]},{"bom-ref":"pkg:npm/universal-user-agent@6.0.0?package-id=dce001152ebfa89f","type":"library","name":"universal-user-agent","version":"6.0.0","cpe":"cpe:2.3:a:universal-user-agent:universal-user-agent:6.0.0:*:*:*:*:*:*:*","purl":"pkg:npm/universal-user-agent@6.0.0","properties":[{"name":"syft:package:foundBy","value":"javascript-lock-cataloger"},{"name":"syft:package:language","value":"javascript"},{"name":"syft:package:type","value":"npm"},{"name":"syft:package:metadataType","value":"javascript-npm-package-lock-entry"},{"name":"syft:cpe23","value":"cpe:2.3:a:universal-user-agent:universal_user_agent:6.0.0:*:*:*:*:*:*:*"},{"name":"syft:cpe23","value":"cpe:2.3:a:universal_user_agent:universal-user-agent:6.0.0:*:*:*:*:*:*:*"},{"name":"syft:cpe23","value":"cpe:2.3:a:universal_user_agent:universal_user_agent:6.0.0:*:*:*:*:*:*:*"},{"name":"syft:cpe23","value":"cpe:2.3:a:universal-user:universal-user-agent:6.0.0:*:*:*:*:*:*:*"},{"name":"syft:cpe23","value":"cpe:2.3:a:universal-user:universal_user_agent:6.0.0:*:*:*:*:*:*:*"},{"name":"syft:cpe23","value":"cpe:2.3:a:universal_user:universal-user-agent:6.0.0:*:*:*:*:*:*:*"},{"name":"syft:cpe23","value":"cpe:2.3:a:universal_user:universal_user_agent:6.0.0:*:*:*:*:*:*:*"},{"name":"syft:cpe23","value":"cpe:2.3:a:universal:universal-user-agent:6.0.0:*:*:*:*:*:*:*"},{"name":"syft:cpe23","value":"cpe:2.3:a:universal:universal_user_agent:6.0.0:*:*:*:*:*:*:*"},{"name":"syft:location:0:path","value":"\\package-lock.json"}]},{"bom-ref":"pkg:npm/webidl-conversions@3.0.1?package-id=4f8a5a9998744b20","type":"library","name":"webidl-conversions","version":"3.0.1","cpe":"cpe:2.3:a:webidl-conversions:webidl-conversions:3.0.1:*:*:*:*:*:*:*","purl":"pkg:npm/webidl-conversions@3.0.1","properties":[{"name":"syft:package:foundBy","value":"javascript-lock-cataloger"},{"name":"syft:package:language","value":"javascript"},{"name":"syft:package:type","value":"npm"},{"name":"syft:package:metadataType","value":"javascript-npm-package-lock-entry"},{"name":"syft:cpe23","value":"cpe:2.3:a:webidl-conversions:webidl_conversions:3.0.1:*:*:*:*:*:*:*"},{"name":"syft:cpe23","value":"cpe:2.3:a:webidl_conversions:webidl-conversions:3.0.1:*:*:*:*:*:*:*"},{"name":"syft:cpe23","value":"cpe:2.3:a:webidl_conversions:webidl_conversions:3.0.1:*:*:*:*:*:*:*"},{"name":"syft:cpe23","value":"cpe:2.3:a:webidl:webidl-conversions:3.0.1:*:*:*:*:*:*:*"},{"name":"syft:cpe23","value":"cpe:2.3:a:webidl:webidl_conversions:3.0.1:*:*:*:*:*:*:*"},{"name":"syft:location:0:path","value":"\\package-lock.json"}]},{"bom-ref":"pkg:npm/whatwg-url@5.0.0?package-id=5f20ba3f03918dab","type":"library","name":"whatwg-url","version":"5.0.0","cpe":"cpe:2.3:a:whatwg-url:whatwg-url:5.0.0:*:*:*:*:*:*:*","purl":"pkg:npm/whatwg-url@5.0.0","properties":[{"name":"syft:package:foundBy","value":"javascript-lock-cataloger"},{"name":"syft:package:language","value":"javascript"},{"name":"syft:package:type","value":"npm"},{"name":"syft:package:metadataType","value":"javascript-npm-package-lock-entry"},{"name":"syft:cpe23","value":"cpe:2.3:a:whatwg-url:whatwg_url:5.0.0:*:*:*:*:*:*:*"},{"name":"syft:cpe23","value":"cpe:2.3:a:whatwg_url:whatwg-url:5.0.0:*:*:*:*:*:*:*"},{"name":"syft:cpe23","value":"cpe:2.3:a:whatwg_url:whatwg_url:5.0.0:*:*:*:*:*:*:*"},{"name":"syft:cpe23","value":"cpe:2.3:a:whatwg:whatwg-url:5.0.0:*:*:*:*:*:*:*"},{"name":"syft:cpe23","value":"cpe:2.3:a:whatwg:whatwg_url:5.0.0:*:*:*:*:*:*:*"},{"name":"syft:location:0:path","value":"\\package-lock.json"}]},{"bom-ref":"pkg:npm/wrappy@1.0.2?package-id=312da465e8ae53de","type":"library","name":"wrappy","version":"1.0.2","cpe":"cpe:2.3:a:wrappy:wrappy:1.0.2:*:*:*:*:*:*:*","purl":"pkg:npm/wrappy@1.0.2","properties":[{"name":"syft:package:foundBy","value":"javascript-lock-cataloger"},{"name":"syft:package:language","value":"javascript"},{"name":"syft:package:type","value":"npm"},{"name":"syft:package:metadataType","value":"javascript-npm-package-lock-entry"},{"name":"syft:location:0:path","value":"\\package-lock.json"}]}]}
